smt_explainability/__init__.py
smt_explainability-0.1.1.dist-info/LICENSE
smt_explainability-0.1.1.dist-info/METADATA
smt_explainability-0.1.1.dist-info/WHEEL
smt_explainability-0.1.1.dist-info/top_level.txt
smt_explainability-0.1.1.dist-info/RECORD
